[{"id":"16","user_id":"16","videofile":"https:\/\/limray.com\/embed\/94\/","imagefile":"news_18_headline.jpeg","title":"Headline News 18 Lokmat","channel":"News 18 Lokmat","description":"","Date":"2019-07-09","sysdate":"2019-07-09 07:30:00","type":"1"},{"id":"10","user_id":"16","videofile":"https:\/\/limray.com\/embed\/e2E\/","imagefile":"sandesh_headline.jpeg","title":"Headline Sandesh TV","channel":"Sandesh TV News","description":"","Date":"2019-05-27","sysdate":"2019-05-27 09:47:17","type":"2"},{"id":"8","user_id":"16","videofile":"https:\/\/limray.com\/embed\/3aq\/","imagefile":"l-band-ssamtv.jpg","title":"L-Band Saam TV","channel":"Saam TV News","description":"","Date":"2019-05-27","sysdate":"2019-05-27 09:45:16","type":"3"},{"id":"7","user_id":"16","videofile":"https:\/\/limray.com\/embed\/V4v\/","imagefile":"l-ban-vtvnews.jpg","title":"L-Band VTV News","channel":"VTV News","description":"","Date":"2019-05-27","sysdate":"2019-05-27 09:44:24","type":"4"},{"id":"9","user_id":"16","videofile":"https:\/\/limray.com\/embed\/XA0\/","imagefile":"aston-band-news18lokmat.jpg","title":"Aston-Band News 18 Lokmat","channel":"News 18 Lokmat","description":"","Date":"2019-05-27","sysdate":"2019-05-27 09:46:15","type":"5"},{"id":"11","user_id":"16","videofile":"https:\/\/limray.com\/embed\/rax\/","imagefile":"l-band-new18lokmat.jpg","title":"L-Band News 18 Lokmat","channel":"News 18 Lokmat","description":"","Date":"2019-05-28","sysdate":"2019-05-28 11:36:19","type":"6"}]